{
  "looting": {
    "items": [
      {
        "count": 1,
        "id": 3035
      }
    ],
    "maxDanger": 10,
    "minCapacity": 100,
    "containers": [
      {
        "count": 1,
        "id": 23721
      }
    ],
    "everyItem": false
  },
  "targeting": [
    {
      "lureDelay": 250,
      "lureMin": 1,
      "maxDistance": 10,
      "anchorRange": 3,
      "lureCount": 2,
      "avoidAttacks": false,
      "rePositionAmount": 5,
      "lureMax": 3,
      "regex": "^.*$",
      "chase": true,
      "priority": 1,
      "keepDistance": true,
      "closeLure": false,
      "danger": 1,
      "keepDistanceRange": 2,
      "lure": true,
      "dynamicLureDelay": false,
      "dynamicLure": false,
      "faceMonster": false,
      "lureCavebot": true,
      "dontLoot": false,
      "diamondArrows": false,
      "delayFrom": 2,
      "anchor": true,
      "closeLureAmount": 3,
      "rePosition": false,
      "name": "*",
      "rpSafe": false
    }
  ]
}